<screen name="E2Kodi_Menu" position="center,center" size="1820,980" title="EmuKodi_Menu">
  <panel name="PKTeamClock" />
  <panel name="PKTeamKey" />
  <panel name="PKTeamKeyRedFull" />
  <panel name="PKTeamKeyGreenFull" />
  <panel name="PKTeamKeyYellFull" />
  <panel name="PKTeamKeyBlueFull" />
  <widget source="list" render="Listbox" position="71,72" size="933,760" enableWrapAround="1" scrollbarWidth="10" scrollbarSliderBorderWidth="1" scrollbarSliderForegroundColor="white" scrollbarSliderBorderColor="white" backgroundColor="background" scrollbarMode="showOnDemand">
    <convert type="TemplatedMultiContent">
                {"template": [
        MultiContentEntryPixmapAlphaTest(pos = (12, 8), size = (120, 75), png = 0),
        MultiContentEntryText(pos = (138, 8), size = (760, 75), font=0, flags = RT_HALIGN_LEFT|RT_VALIGN_CENTER, text = 1),
            ],
        "fonts": [gFont("Regular", 26)],
        "itemHeight": 75
                        }
      </convert>
  </widget>
  <ePixmap pixmap="PLi-FullNightHD-Mod-M-PY3/logo/logo_hyper.png" position="1234,494" size="519,91" alphatest="on" transparent="0" />
</screen>